sharewifi.py
sharewifi-1.0.5.dist-info/METADATA
sharewifi-1.0.5.dist-info/WHEEL
sharewifi-1.0.5.dist-info/entry_points.txt
sharewifi-1.0.5.dist-info/top_level.txt
sharewifi-1.0.5.dist-info/RECORD
